llamaindex_primordia/__init__.py
llamaindex_primordia/callback.py
llamaindex_primordia-0.1.0.dist-info/METADATA
llamaindex_primordia-0.1.0.dist-info/WHEEL
llamaindex_primordia-0.1.0.dist-info/RECORD
