Metadata-Version: 2.4
Name: llamaindex-primordia
Version: 0.1.0
Summary: Primordia metering for LlamaIndex
Project-URL: Kernel, https://clearing.kaledge.app
License-Expression: MIT
Requires-Python: >=3.9
Requires-Dist: llama-index-core>=0.10.0
